LICENSE
MANIFEST.in
README.md
README.rst
pyproject.toml
setup.cfg
setup.py
controller/__init__.py
controller/__main__.py
controller/app.py
controller/builds.py
controller/compose.py
controller/dockerizing.py
controller/gitter.py
controller/packages.py
controller/project.py
controller/templating.py
controller/commands/__init__.py
controller/commands/add.py
controller/commands/ancestors.py
controller/commands/backup.py
controller/commands/build.py
controller/commands/check.py
controller/commands/create.py
controller/commands/dhparam.py
controller/commands/dump.py
controller/commands/init.py
controller/commands/install.py
controller/commands/interfaces.py
controller/commands/list.py
controller/commands/logs.py
controller/commands/pull.py
controller/commands/remove.py
controller/commands/restart.py
controller/commands/scale.py
controller/commands/shell.py
controller/commands/ssl.py
controller/commands/start.py
controller/commands/status.py
controller/commands/stop.py
controller/commands/update.py
controller/commands/upgrade.py
controller/commands/verify.py
controller/commands/version.py
controller/commands/volatile.py
controller/confs/angular.yml
controller/confs/backend.yml
controller/confs/projects_defaults.yaml
controller/confs/projects_prod_defaults.yaml
controller/confs/react.yml
controller/templates/activate_account.html.j2
controller/templates/commons.yml.j2
controller/templates/component_template.html.j2
controller/templates/component_template.ts.j2
controller/templates/custom.footer.html.j2
controller/templates/custom.footer.ts.j2
controller/templates/custom.module.ts.j2
controller/templates/custom.navbar.brand.html.j2
controller/templates/custom.navbar.links.html.j2
controller/templates/custom.navbar.ts.j2
controller/templates/custom.profile.html.j2
controller/templates/custom.profile.ts.j2
controller/templates/custom.project.options.ts.j2
controller/templates/development.yml.j2
controller/templates/endpoint_template.py.j2
controller/templates/flake8.j2
rapydo_controller.egg-info/PKG-INFO
rapydo_controller.egg-info/SOURCES.txt
rapydo_controller.egg-info/dependency_links.txt
rapydo_controller.egg-info/entry_points.txt
rapydo_controller.egg-info/requires.txt
rapydo_controller.egg-info/top_level.txt