Metadata-Version: 1.2
Name: rapydo-controller
Version: 0.7.6
Summary: Manage and deploy projects based on RAPyDo framework
Home-page: https://rapydo.github.io/docs
License: MIT
Keywords: http,api,rest,web,backend,rapydo
Platform: UNKNOWN
Classifier: Programming Language :: Python
Classifier: Intended Audience :: Developers
Classifier: Development Status :: 3 - Alpha
Classifier: License :: OSI Approved :: MIT License
Classifier: Programming Language :: Python :: 3.6
Classifier: Programming Language :: Python :: 3.7
Classifier: Programming Language :: Python :: 3.8
Requires-Python: >=3.6.0
